mysql/__init__.py
mysql/connector/__init__.py
mysql/connector/abstracts.py
mysql/connector/authentication.py
mysql/connector/catch23.py
mysql/connector/charsets.py
mysql/connector/connection.py
mysql/connector/connection_cext.py
mysql/connector/constants.py
mysql/connector/conversion.py
mysql/connector/cursor.py
mysql/connector/cursor_cext.py
mysql/connector/custom_types.py
mysql/connector/dbapi.py
mysql/connector/errorcode.py
mysql/connector/errors.py
mysql/connector/network.py
mysql/connector/optionfiles.py
mysql/connector/pooling.py
mysql/connector/protocol.py
mysql/connector/utils.py
mysql/connector/version.py
mysql/connector/django/__init__.py
mysql/connector/django/base.py
mysql/connector/django/client.py
mysql/connector/django/compiler.py
mysql/connector/django/creation.py
mysql/connector/django/features.py
mysql/connector/django/introspection.py
mysql/connector/django/operations.py
mysql/connector/django/schema.py
mysql/connector/django/validation.py
mysql/connector/locales/__init__.py
mysql/connector/locales/eng/__init__.py
mysql/connector/locales/eng/client_error.py
mysqlpy-8.0.12.dist-info/METADATA
mysqlpy-8.0.12.dist-info/RECORD
mysqlpy-8.0.12.dist-info/WHEEL
mysqlpy-8.0.12.dist-info/top_level.txt
mysqlx/__init__.py
mysqlx/authentication.py
mysqlx/charsets.py
mysqlx/compat.py
mysqlx/connection.py
mysqlx/constants.py
mysqlx/crud.py
mysqlx/dbdoc.py
mysqlx/errorcode.py
mysqlx/errors.py
mysqlx/expr.py
mysqlx/helpers.py
mysqlx/protocol.py
mysqlx/result.py
mysqlx/statement.py
mysqlx/locales/__init__.py
mysqlx/locales/eng/__init__.py
mysqlx/locales/eng/client_error.py
mysqlx/protobuf/__init__.py
mysqlx/protobuf/mysqlx_connection_pb2.py
mysqlx/protobuf/mysqlx_crud_pb2.py
mysqlx/protobuf/mysqlx_datatypes_pb2.py
mysqlx/protobuf/mysqlx_expect_pb2.py
mysqlx/protobuf/mysqlx_expr_pb2.py
mysqlx/protobuf/mysqlx_notice_pb2.py
mysqlx/protobuf/mysqlx_pb2.py
mysqlx/protobuf/mysqlx_resultset_pb2.py
mysqlx/protobuf/mysqlx_session_pb2.py
mysqlx/protobuf/mysqlx_sql_pb2.py
