Metadata-Version: 1.1
Name: mysqlpy
Version: 8.0.12
Summary: MySQL driver written in Python
Home-page: http://dev.mysql.com/doc/connector-python/en/index.html
Author: Oracle and/or its affiliates
Author-email: UNKNOWN
License: GNU GPLv2 (with FOSS License Exception)
Download-URL: http://dev.mysql.com/downloads/connector/python/
Keywords: mysql db
Platform: UNKNOWN
Classifier: Development Status :: 5 - Production/Stable
Classifier: Environment :: Other Environment
Classifier: Intended Audience :: Developers
Classifier: Intended Audience :: Education
Classifier: Intended Audience :: Information Technology
Classifier: Intended Audience :: System Administrators
Classifier: License :: OSI Approved :: GNU General Public License (GPL)
Classifier: Operating System :: OS Independent
Classifier: Programming Language :: Python :: 2.7
Classifier: Programming Language :: Python :: 3
Classifier: Programming Language :: Python :: 3.4
Classifier: Programming Language :: Python :: 3.5
Classifier: Programming Language :: Python :: 3.6
Classifier: Topic :: Database
Classifier: Topic :: Software Development
Classifier: Topic :: Software Development :: Libraries :: Application Frameworks
Classifier: Topic :: Software Development :: Libraries :: Python Modules
